[
  {
    "Week 1": [
      {
        "topic": "circular linked list Data Structures implementation",
        "video": "https://www.youtube.com/watch?v=HMkdlu5sP4A"
      },
      {
        "topic": "doubly linked list Data Structures reverse recursive",
        "video": "https://www.youtube.com/watch?v=63HJ2-jV6Mk"
      },
      {
        "topic": "Data Structures array vs arraylist performance analysis",
        "video": "https://www.youtube.com/watch?v=ft0owvS5tQA"
      },
      {
        "topic": "advanced Data Structures array manipulation techniques",
        "video": "https://www.youtube.com/watch?v=bxRVz8zklWM"
      },
      {
        "topic": "Data Structures stack problems for interviews",
        "video": "https://www.youtube.com/watch?v=cQWr9DFE1ww"
      },
      {
        "topic": "implement Data Structures queue using two stacks",
        "video": "https://www.youtube.com/watch?v=sFvP5Ois0CE"
      },
      {
        "topic": "min heap max heap Data Structures complexities",
        "video": "https://www.youtube.com/watch?v=j6iP4lDTKyI"
      },
      {
        "topic": "priority queue Data Structures advanced applications",
        "video": "https://www.youtube.com/watch?v=m9SVfOYTaBQ"
      },
      {
        "topic": "AVL tree Data Structures rotations explained",
        "video": "https://www.youtube.com/watch?v=zP2xbKerIds"
      },
      {
        "topic": "red black tree Data Structures insertion deletion visualization",
        "video": "https://www.youtube.com/watch?v=94ErZ5K8XZg"
      },
      {
        "topic": "segment tree Data Structures range query update",
        "video": "https://www.youtube.com/watch?v=CWDQJGaN1gY"
      },
      {
        "topic": "trie Data Structures autocomplete implementation",
        "video": "https://www.youtube.com/watch?v=zIjfhVPRZCg"
      },
      {
        "topic": "Dijkstra's algorithm Data Structures shortest path",
        "video": "https://www.youtube.com/watch?v=Gd92jSu_cZk"
      },
      {
        "topic": "Floyd Warshall algorithm Data Structures all pairs shortest path",
        "video": "https://www.youtube.com/watch?v=i9SZKy2yTZw"
      },
      {
        "topic": "minimum spanning tree Data Structures Kruskal's Prim's",
        "video": "https://www.youtube.com/watch?v=h6cUkkaKNHw"
      },
      {
        "topic": "topological sort Data Structures cycle detection",
        "video": "https://www.youtube.com/watch?v=ChxA6H2253I"
      },
      {
        "topic": "collision resolution techniques Data Structures open addressing",
        "video": "https://www.youtube.com/watch?v=j612Fj-mgCY"
      },
      {
        "topic": "custom hash function Data Structures implementation guide",
        "video": "https://www.youtube.com/watch?v=0wFI04w345k"
      },
      {
        "topic": "disjoint set union find Data Structures path compression by rank",
        "video": "https://www.youtube.com/watch?v=xxHKEnHjLyw"
      },
      {
        "topic": "union by rank Data Structures find by path compression explained",
        "video": "https://www.youtube.com/watch?v=sk46MJ_h8Sk"
      },
      {
        "topic": "dynamic programming problems Data Structures tabulation",
        "video": "https://www.youtube.com/watch?v=sWnBVPRA0yQ"
      },
      {
        "topic": "greedy algorithms Data Structures optimization problems",
        "video": "https://www.youtube.com/watch?v=zPtI8q9gvX8"
      },
      {
        "topic": "memoization vs tabulation Data Structures problems",
        "video": "https://www.youtube.com/watch?v=5dRGRueKU3M"
      },
      {
        "topic": "knapsack problem Data Structures dynamic programming variations",
        "video": "https://www.youtube.com/watch?v=PfkBS9qIMRE"
      },
      {
        "topic": "top 50 Data Structures interview questions",
        "video": "https://www.youtube.com/watch?v=2AckU9AZc0w"
      },
      {
        "topic": "hard Data Structures problems for placements",
        "video": "https://www.youtube.com/watch?v=Nx4bvwU0DqE"
      },
      {
        "topic": "Big O notation Data Structures time space complexity analysis",
        "video": "https://www.youtube.com/watch?v=FPu9Uld7W-E"
      },
      {
        "topic": "system design Data Structures choices discussion",
        "video": "https://www.youtube.com/watch?v=-mN3VyJuCjM"
      }
    ]
  }
]